omicsdata/__init__.py
omicsdata/cn/estimate.py
omicsdata/csv/parse.py
omicsdata/npz/__init__.py
omicsdata/npz/archive.py
omicsdata/ssm/__init__.py
omicsdata/ssm/columns.py
omicsdata/ssm/common.py
omicsdata/ssm/constants.py
omicsdata/ssm/convert.py
omicsdata/ssm/parse.py
omicsdata/ssm/ssm_to_pyclone.py
omicsdata/ssm/supervariants.py
omicsdata/ssm/_convert/__init__.py
omicsdata/ssm/_convert/ssm_to_pyclone.py
omicsdata/ssm/_convert/ssm_to_viber.py
omicsdata/ssm/_convert/convert_extra/ssm_base_converter.py
omicsdata/ssm/_convert/convert_extra/ssm_to_fastclone.py
omicsdata/ssm/_convert/convert_extra/ssm_to_mobster_tsv.py
omicsdata/ssm/_convert/convert_extra/ssm_to_pcvi_tsv.py
omicsdata/ssm/_convert/convert_extra/ssm_to_scc_tsv.py
omicsdata/ssm/_convert/convert_extra/ssm_to_viber_tsv.py
omicsdata/ssm/_convert/convert_extra/vcf_to_ssm.py
omicsdata/tree/__init__.py
omicsdata/tree/adj.py
omicsdata/tree/columns.py
omicsdata/tree/newick.py
omicsdata/tree/parents.py
omicsdata/tree/neutree/__init__.py
omicsdata-1.3.dist-info/LICENSE
omicsdata-1.3.dist-info/METADATA
omicsdata-1.3.dist-info/WHEEL
omicsdata-1.3.dist-info/top_level.txt
omicsdata-1.3.dist-info/RECORD
