Metadata-Version: 2.1
Name: omicsdata
Version: 1.3
Summary: A package for manipulating omics data file types
Author-email: ethanumn <kulma009@umn.edu>
Project-URL: Homepage, https://github.com/ethanumn/omicsdata
Project-URL: Bug Tracker, https://github.com/ethanumn/omicsdata/issues
Classifier: Programming Language :: Python :: 3
Classifier: License :: OSI Approved :: MIT License
Classifier: Operating System :: OS Independent
Requires-Python: >=3.10
License-File: LICENSE
